phenocv/__init__.py
phenocv/registry.py
phenocv/utils.py
phenocv/analysis/__init__.py
phenocv/analysis/traits.py
phenocv/configs/sahi_panicle_headingdate.cfg
phenocv/configs/sahi_panicle_num.cfg
phenocv/configs/test.cfg
phenocv/configs/mmdet/_base_/custom_runtime.py
phenocv/configs/mmdet/_base_/models/cascade-rcnn_r50_fpn.py
phenocv/configs/mmdet/_base_/models/faster-rcnn_r50_fpn.py
phenocv/configs/mmdet/_base_/models/mask-rcnn_r50_fpn.py
phenocv/configs/mmdet/_base_/schedules/schedule_100e_onecycle.py
phenocv/configs/mmdet/_base_/schedules/schedule_1x.py
phenocv/configs/mmdet/_base_/schedules/schedule_20e.py
phenocv/configs/mmdet/_base_/schedules/schedule_2x.py
phenocv/configs/mmdet/_base_/schedules/schedule_3x.py
phenocv/configs/mmdet/panicle/cascade-rcnn_convnext-t-p4-w7_fpn_2x_panicle-full.py
phenocv/configs/mmdet/panicle/cascade-rcnn_r101_fpn_2x_panicle-full.py
phenocv/configs/mmdet/panicle/cascade-rcnn_r50_fpn_2x_panicle-full.py
phenocv/configs/mmdet/panicle/dino-4scale_r50_8xb2-2x_panicle-full.py
phenocv/configs/mmdet/panicle/dino-5scale_swim-l_8xb2-2x_panicle-full.py
phenocv/configs/mmdet/panicle/faster-rcnn_convnext-t-p4-w7_fpn_3x_ms_panicle-full.py
phenocv/configs/mmdet/panicle/faster-rcnn_r101_fpn_2x_panicle-full.py
phenocv/configs/mmdet/panicle/faster-rcnn_r50-scratch_fpn_fn-all_6x_panicle-full.py
phenocv/configs/mmdet/panicle/faster-rcnn_r50_fpn_2x_panicle-full.py
phenocv/convert/__init__.py
phenocv/convert/base.py
phenocv/convert/coco2ls.py
phenocv/convert/yolo2coco.py
phenocv/predict/__init__.py
phenocv/predict/base_yolo.py
phenocv/predict/utils.py
phenocv/predict/yolo.py
phenocv/process/__init__.py
phenocv/process/base.py
phenocv/process/extractor.py
phenocv/process/formatter.py
phenocv/process/postprocessor.py
phenocv/process/preprocess.py
phenocv/process/utils.py
phenocv-0.1.4.dist-info/LICENSE
phenocv-0.1.4.dist-info/METADATA
phenocv-0.1.4.dist-info/WHEEL
phenocv-0.1.4.dist-info/top_level.txt
phenocv-0.1.4.dist-info/RECORD
