Metadata-Version: 2.1
Name: phenocv
Version: 0.1.4
Summary: Rice High Throughput Phenotyping Computer Vision Toolkit
Author-email: RuLei Chen <chenrulei@cemps.ac.cn>
Maintainer-email: RuLei Chen <chenrulei@cemps.ac.cn>
License: AGPL-3.0
Keywords: machine-learning,deep-learning,computer-vision,ML,DL,AI,YOLO
Classifier: Development Status :: 4 - Beta
Classifier: Intended Audience :: Developers
Classifier: Intended Audience :: Science/Research
Classifier: License :: OSI Approved :: GNU Affero General Public License v3 or later (AGPLv3+)
Classifier: Programming Language :: Python :: 3
Classifier: Programming Language :: Python :: 3.8
Classifier: Programming Language :: Python :: 3.9
Classifier: Programming Language :: Python :: 3.10
Classifier: Programming Language :: Python :: 3.11
Classifier: Topic :: Software Development
Classifier: Topic :: Scientific/Engineering
Classifier: Topic :: Scientific/Engineering :: Artificial Intelligence
Classifier: Topic :: Scientific/Engineering :: Image Recognition
Classifier: Operating System :: POSIX :: Linux
Classifier: Operating System :: MacOS
Classifier: Operating System :: Microsoft :: Windows
Requires-Python: >=3.8
License-File: LICENSE
Requires-Dist: albumentations
Requires-Dist: catalogue
Requires-Dist: confection
Requires-Dist: matplotlib
Requires-Dist: numpy
Requires-Dist: opencv-python
Requires-Dist: pandas
Requires-Dist: pycocotools
Requires-Dist: sahi
Requires-Dist: scikit-learn
Requires-Dist: scipy
Requires-Dist: segment-anything ==1.0
Requires-Dist: segment-anything-hq ==0.3
Requires-Dist: setuptools
Requires-Dist: timm
Requires-Dist: torch
Requires-Dist: torchvision
Requires-Dist: tqdm
Requires-Dist: ultralytics >=8.1.0
Provides-Extra: dev
Requires-Dist: ipython ; extra == 'dev'
Requires-Dist: check-manifest ; extra == 'dev'
Requires-Dist: pre-commit ; extra == 'dev'
Requires-Dist: pytest ; extra == 'dev'
Requires-Dist: pytest-cov ; extra == 'dev'
Requires-Dist: coverage[toml] ; extra == 'dev'
Requires-Dist: mkdocs-material ; extra == 'dev'
Requires-Dist: mkdocstrings[python] ; extra == 'dev'
Requires-Dist: mkdocs-jupyter ; extra == 'dev'
Provides-Extra: label_studio
Requires-Dist: label-studio-converter ==0.0.55 ; extra == 'label_studio'
Requires-Dist: label-studio-ml ==1.0.9 ; extra == 'label_studio'
Requires-Dist: label-studio-tools ==0.0.3 ; extra == 'label_studio'
